octobot_tentacles_manager/__init__.py
octobot_tentacles_manager/cli.py
octobot_tentacles_manager/constants.py
octobot_tentacles_manager/enums.py
octobot_tentacles_manager/api/__init__.py
octobot_tentacles_manager/api/configurator.py
octobot_tentacles_manager/api/creator.py
octobot_tentacles_manager/api/inspector.py
octobot_tentacles_manager/api/installer.py
octobot_tentacles_manager/api/loader.py
octobot_tentacles_manager/api/uninstaller.py
octobot_tentacles_manager/api/updater.py
octobot_tentacles_manager/api/uploader.py
octobot_tentacles_manager/api/util/__init__.py
octobot_tentacles_manager/api/util/tentacles_management.py
octobot_tentacles_manager/configuration/__init__.py
octobot_tentacles_manager/configuration/config_file.py
octobot_tentacles_manager/configuration/tentacle_configuration.py
octobot_tentacles_manager/configuration/tentacles_setup_configuration.py
octobot_tentacles_manager/creators/__init__.py
octobot_tentacles_manager/creators/compiled_package_manager.py
octobot_tentacles_manager/creators/tentacle_creator.py
octobot_tentacles_manager/creators/templates/Mode_config.template
octobot_tentacles_manager/creators/templates/Mode_tentacle.template
octobot_tentacles_manager/creators/templates/RealTime_tentacle.template
octobot_tentacles_manager/creators/templates/Social_tentacle.template
octobot_tentacles_manager/creators/templates/Strategies_config.template
octobot_tentacles_manager/creators/templates/Strategies_tentacle.template
octobot_tentacles_manager/creators/templates/TA_tentacle.template
octobot_tentacles_manager/creators/templates/Util_tentacle.template
octobot_tentacles_manager/creators/templates/description_tentacle.template
octobot_tentacles_manager/exporters/__init__.py
octobot_tentacles_manager/exporters/artifact_exporter.py
octobot_tentacles_manager/exporters/tentacle_bundle_exporter.py
octobot_tentacles_manager/exporters/tentacle_exporter.py
octobot_tentacles_manager/exporters/tentacle_package_exporter.py
OctoBot_Tentacles_Manager-2.8.6.dist-info/LICENSE
OctoBot_Tentacles_Manager-2.8.6.dist-info/METADATA
OctoBot_Tentacles_Manager-2.8.6.dist-info/WHEEL
OctoBot_Tentacles_Manager-2.8.6.dist-info/entry_points.txt
OctoBot_Tentacles_Manager-2.8.6.dist-info/top_level.txt
OctoBot_Tentacles_Manager-2.8.6.dist-info/RECORD
