Metadata-Version: 2.1
Name: OctoBot-Tentacles-Manager
Version: 2.8.6
Summary: OctoBot project module installer
Home-page: https://github.com/Drakkar-Software/OctoBot-Tentacles-Manager
Author: Drakkar-Software
Author-email: drakkar-software@protonmail.com
License: LGPL-3.0
Platform: UNKNOWN
Classifier: Development Status :: 5 - Production/Stable
Classifier: Operating System :: OS Independent
Classifier: Operating System :: MacOS :: MacOS X
Classifier: Operating System :: Microsoft :: Windows
Classifier: Operating System :: POSIX
Classifier: Programming Language :: Python :: 3.8
Classifier: Programming Language :: Python :: 3.9
Requires-Python: >=3.8
Requires-Dist: setuptools
Requires-Dist: OctoBot-Commons (<1.9,>=1.8)
Requires-Dist: aiofiles (<0.7,>=0.6.0)
Requires-Dist: aiohttp (>=3.8.1)
Requires-Dist: jinja2 (>=3.0.3)
Requires-Dist: pyyaml (>=6.0)
Requires-Dist: packaging (==21.3)
Requires-Dist: aioboto3 (==9.3.1)
